pypassist/__init__.py
pypassist/exceptions.py
pypassist/version.py
pypassist/dataclass/__init__.py
pypassist/dataclass/exceptions.py
pypassist/dataclass/decorators/__init__.py
pypassist/dataclass/decorators/base.py
pypassist/dataclass/decorators/exportable/__init__.py
pypassist/dataclass/decorators/exportable/decorator.py
pypassist/dataclass/decorators/exportable/exceptions.py
pypassist/dataclass/decorators/exportable/exportable.py
pypassist/dataclass/decorators/exportable/setup.py
pypassist/dataclass/decorators/exportable/validation.py
pypassist/dataclass/decorators/exportable/strategy/__init__.py
pypassist/dataclass/decorators/exportable/strategy/base.py
pypassist/dataclass/decorators/exportable/strategy/type/__init__.py
pypassist/dataclass/decorators/exportable/strategy/type/default.py
pypassist/dataclass/decorators/exportable/strategy/type/registry.py
pypassist/dataclass/decorators/exportable/strategy/type/runner.py
pypassist/dataclass/decorators/exportable/strategy/type/wenv.py
pypassist/dataclass/decorators/registry/__init__.py
pypassist/dataclass/decorators/registry/decorator.py
pypassist/dataclass/decorators/registry/exceptions.py
pypassist/dataclass/decorators/registry/handlers.py
pypassist/dataclass/decorators/registry/setup.py
pypassist/dataclass/decorators/runner/__init__.py
pypassist/dataclass/decorators/runner/decorator.py
pypassist/dataclass/decorators/runner/exceptions.py
pypassist/dataclass/decorators/viewer/__init__.py
pypassist/dataclass/decorators/viewer/decorator.py
pypassist/dataclass/decorators/viewer/exceptions.py
pypassist/dataclass/decorators/viewer/setup.py
pypassist/dataclass/decorators/viewer/validation.py
pypassist/dataclass/decorators/wenv/__init__.py
pypassist/dataclass/decorators/wenv/decorator.py
pypassist/dataclass/decorators/wenv/dict_field.py
pypassist/dataclass/decorators/wenv/exceptions.py
pypassist/dataclass/decorators/wenv/setup.py
pypassist/dataclass/decorators/wenv/validation.py
pypassist/dataclass/format/__init__.py
pypassist-0.2.4.dist-info/METADATA
pypassist-0.2.4.dist-info/WHEEL
pypassist-0.2.4.dist-info/licenses/LICENSE.txt
pypassist-0.2.4.dist-info/RECORD
