Metadata-Version: 2.4
Name: PypAssist
Version: 0.2.4
Summary: A library gathering utilities for python packages development.
Project-URL: Homepage, https:/gitlab.com/pypassist/pypassist
Project-URL: Source, https://gitlab.com/pypassist/pypassist.git
Project-URL: Issues, https://gitlab.com/pypassist/pypassist/-/issues
Author-email: Arnaud Duvermy <arnaud.duvermy@gmail.com>
License: MIT License
License-File: LICENSE.txt
Classifier: License :: OSI Approved :: MIT License
Classifier: Operating System :: OS Independent
Classifier: Programming Language :: Python :: 3
Requires-Python: >=3.7
Requires-Dist: docstring-parser
Requires-Dist: jrai-common-mixins
Requires-Dist: pydantic
Requires-Dist: pyyaml
Provides-Extra: workflow
Requires-Dist: dagster; extra == 'workflow'
Requires-Dist: hydra-core; extra == 'workflow'
